panda_robot/__init__.py
panda_robot/panda_kinematics.py
panda_robot/panda_robot.py
panda_robot/utils/__init__.py
panda_robot/utils/kdl_parser.py
panda_robot/utils/math_utils.py
panda_robot-0.0.5.dist-info/LICENSE
panda_robot-0.0.5.dist-info/METADATA
panda_robot-0.0.5.dist-info/NOTICE
panda_robot-0.0.5.dist-info/WHEEL
panda_robot-0.0.5.dist-info/top_level.txt
panda_robot-0.0.5.dist-info/RECORD
