Metadata-Version: 2.1
Name: panda-robot
Version: 0.0.5
Summary: Unified ROS-Python API for Franka Emika Panda robot using Franka ROS Interface
Home-page: https://justagist.github.io/panda_robot
Author: Saif Sidhik
Author-email: sxs1412@bham.ac.uk
Maintainer: Saif Sidhik
Maintainer-email: sxs1412@bham.ac.uk
License: Apache 2.0
Project-URL: Bug Tracker, https://github.com/justagist/panda_robot/issues
Project-URL: Documentation, https://justagist.github.io/panda_robot/DOC
Project-URL: Source Code, https://github.com/justagist/panda_robot
Platform: UNKNOWN
Classifier: License :: OSI Approved :: Apache Software License
Classifier: Programming Language :: Python :: 2.7
Classifier: Programming Language :: Python :: 3.6
Classifier: Programming Language :: Python :: 3.7
Classifier: Programming Language :: Python :: 3.8
Classifier: Topic :: Software Development :: Libraries :: Python Modules
Classifier: Framework :: Robot Framework :: Library
Requires-Dist: numpy (>=1.16.6)
Requires-Dist: numpy-quaternion (==2021.4.5.14.42.35)
